MANIFEST.in
setup.py
more_ascii_art/__init__.py
more_ascii_art/cat.py
more_ascii_art/chicken.py
more_ascii_art/elephant.py
more_ascii_art/mouse.py
more_ascii_art.egg-info/PKG-INFO
more_ascii_art.egg-info/SOURCES.txt
more_ascii_art.egg-info/dependency_links.txt
more_ascii_art.egg-info/not-zip-safe
more_ascii_art.egg-info/top_level.txt