Metadata-Version: 1.0
Name: more_ascii_art
Version: 1.3
Summary: Cool ASCII art with python
Home-page: http://github.com/PenetratingShot/Python-ASCII-Art
Author: Shreyas Lad and Talon Bragg
Author-email: slad0716@gmail.com
License: MIT
Platform: UNKNOWN
